LICENSE.txt
MANIFEST.in
README.txt
metadata.py
setup.cfg
setup.py
django_localeurl.egg-info/PKG-INFO
django_localeurl.egg-info/SOURCES.txt
django_localeurl.egg-info/dependency_links.txt
django_localeurl.egg-info/top_level.txt
docs/history.rst
docs/index.rst
docs/setup.rst
docs/usage.rst
localeurl/__init__.py
localeurl/middleware.py
localeurl/models.py
localeurl/settings.py
localeurl/sitemaps.py
localeurl/urls.py
localeurl/utils.py
localeurl/views.py
localeurl/templatetags/__init__.py
localeurl/templatetags/localeurl_tags.py