Metadata-Version: 1.0
Name: django-localeurl
Version: 1.4
Summary: A Django application that allow you to specify the language of a page in the URL.
Home-page: http://packages.python.org/django-localeurl/
Author: Carl Meyer
Author-email: carl@oddbird.net
License: MIT License
Keywords: django i18n
Platform: UNKNOWN
Classifier: Development Status :: 5 - Production/Stable
Classifier: Environment :: Web Environment
Classifier: Framework :: Django
Classifier: Intended Audience :: Developers
Classifier: License :: OSI Approved :: MIT License
Classifier: Operating System :: OS Independent
Classifier: Programming Language :: Python
Classifier: Topic :: Software Development :: Libraries :: Application Frameworks
Classifier: Topic :: Software Development :: Libraries :: Python Modules
Classifier: Topic :: Software Development :: Localization
